aiotask_context/__init__.py
aiotask_context-0.6.1.dist-info/LICENSE
aiotask_context-0.6.1.dist-info/METADATA
aiotask_context-0.6.1.dist-info/WHEEL
aiotask_context-0.6.1.dist-info/top_level.txt
aiotask_context-0.6.1.dist-info/RECORD
